s3p_sdk/__init__.py
s3p_sdk/abstracts/__init__.py
s3p_sdk/abstracts/abstract_repository.py
s3p_sdk/exceptions/__init__.py
s3p_sdk/exceptions/parser.py
s3p_sdk/module/__init__.py
s3p_sdk/plugin/__init__.py
s3p_sdk/plugin/config/__init__.py
s3p_sdk/plugin/config/abc_object.py
s3p_sdk/plugin/config/coreconfig.py
s3p_sdk/plugin/config/middlewareconfig.py
s3p_sdk/plugin/config/modules/__init__.py
s3p_sdk/plugin/config/modules/abc_module.py
s3p_sdk/plugin/config/modules/cut_junk_characters_from_doc_text.py
s3p_sdk/plugin/config/modules/download_documents_asset_with_selenium.py
s3p_sdk/plugin/config/modules/filter_only_new_document.py
s3p_sdk/plugin/config/modules/save_document.py
s3p_sdk/plugin/config/modules/save_only_new_documents.py
s3p_sdk/plugin/config/modules/timezone_safe_control.py
s3p_sdk/plugin/config/modules/upload_to_s3.py
s3p_sdk/plugin/config/payload/__init__.py
s3p_sdk/plugin/config/payload/entry/__init__.py
s3p_sdk/plugin/config/payload/entry/abc_param.py
s3p_sdk/plugin/config/payload/entry/const_param_config.py
s3p_sdk/plugin/config/payload/entry/file_param_config.py
s3p_sdk/plugin/config/payload/entry/module_param_config.py
s3p_sdk/plugin/config/restrictconfig.py
s3p_sdk/plugin/config/taskconfig.py
s3p_sdk/plugin/config/trigger.py
s3p_sdk/plugin/payloads/__init__.py
s3p_sdk/plugin/payloads/abc_payload_base.py
s3p_sdk/plugin/payloads/parsers/__init__.py
s3p_sdk/plugin/payloads/parsers/abc_parser_base.py
s3p_sdk/plugin/payloads/parsers/force_parser_base.py
s3p_sdk/plugin/payloads/parsers/parser_base.py
s3p_sdk/plugin/payloads/payload_base.py
s3p_sdk/plugin/types.py
s3p_sdk/task/__init__.py
s3p_sdk/task/status.py
s3p_sdk/types/__init__.py
s3p_sdk/types/digest.py
s3p_sdk/types/document.py
s3p_sdk/types/export.py
s3p_sdk/types/manifest.py
s3p_sdk/types/node.py
s3p_sdk/types/plugin.py
s3p_sdk/types/plugin_restrictions.py
s3p_sdk/types/refer.py
s3p_sdk/types/role.py
s3p_sdk/types/score.py
s3p_sdk/types/task.py
s3p_sdk/types/user.py
s3p_sdk-0.2.13.dist-info/LICENSE
s3p_sdk-0.2.13.dist-info/METADATA
s3p_sdk-0.2.13.dist-info/WHEEL
s3p_sdk-0.2.13.dist-info/RECORD
